kodict_core/__init__.py
kodict_core/main.py
kodict_core/services/__init__.py
kodict_core/services/deepl.py
kodict_core/services/krdict.py
kodict_core-1.0.0.4.dist-info/LICENSE
kodict_core-1.0.0.4.dist-info/METADATA
kodict_core-1.0.0.4.dist-info/WHEEL
kodict_core-1.0.0.4.dist-info/dependency_links.txt
kodict_core-1.0.0.4.dist-info/top_level.txt
kodict_core-1.0.0.4.dist-info/RECORD
